lookups/__about__.py
lookups/__init__.py
lookups/delegated_lookup.py
lookups/entry_point.py
lookups/generic_lookup.py
lookups/instance_content.py
lookups/lookup.py
lookups/lookups.py
lookups/proxy_lookup.py
lookups/py.typed
lookups/set_storage.py
lookups/simple.py
lookups/singleton.py
lookups/weak_observable.py
lookups-0.3.0.dist-info/LICENSE
lookups-0.3.0.dist-info/METADATA
lookups-0.3.0.dist-info/WHEEL
lookups-0.3.0.dist-info/entry_points.txt
lookups-0.3.0.dist-info/top_level.txt
lookups-0.3.0.dist-info/RECORD
