Metadata-Version: 2.1
Name: lookups
Version: 0.3.0
Summary: DCI lookups in Python (inspired by Netbeans Platform Lookups API)
Home-page: https://github.com/AxelVoitier/lookups
Author: Axel Voitier
Author-email: axel.voitier@gmail.com
License: MPLv2
Keywords: lookup,lookups,dci
Platform: UNKNOWN
Classifier: Development Status :: 4 - Beta
Classifier: Intended Audience :: Developers
Classifier: Topic :: Software Development :: Libraries :: Python Modules
Classifier: Topic :: Software Development :: Object Brokering
Classifier: License :: OSI Approved :: Mozilla Public License 2.0 (MPL 2.0)
Classifier: Programming Language :: Python :: 3 :: Only
Classifier: Programming Language :: Python :: 3.7
Classifier: Programming Language :: Python :: 3.8
Classifier: Programming Language :: Python :: 3.9
Classifier: Typing :: Typed
Requires-Python: ~=3.7
Requires-Dist: observable
Requires-Dist: typing-extensions
Requires-Dist: importlib-metadata ; python_version < "3.8"
Provides-Extra: dev
Requires-Dist: check-manifest ; extra == 'dev'
Requires-Dist: flake8 ; extra == 'dev'
Requires-Dist: mypy ; extra == 'dev'
Requires-Dist: pytest ; extra == 'dev'
Requires-Dist: pytest-cov ; extra == 'dev'
Requires-Dist: pytest-html ; extra == 'dev'
